papayapy/__init__.py
papayapy-0.0.2.dist-info/METADATA
papayapy-0.0.2.dist-info/WHEEL
papayapy-0.0.2.dist-info/top_level.txt
papayapy-0.0.2.dist-info/RECORD
