Metadata-Version: 2.1
Name: papayapy
Version: 0.0.2
Summary: Automate iOS Using Python
Home-page: https://papayapy.com
Author: Example Author
Author-email: hi@papayapy.com
License: UNKNOWN
Platform: UNKNOWN
Classifier: Programming Language :: Python :: 3
Requires-Python: >=3.8
